{
  "result": 1,
  "sessions": [
    {
      "args": {},
      "name": "coverage",
      "result": "success",
      "result_code": 1,
      "signatures": [
        "coverage-3.9"
      ]
    },
    {
      "args": {},
      "name": "coverage",
      "result": "success",
      "result_code": 1,
      "signatures": [
        "coverage-3.10"
      ]
    },
    {
      "args": {},
      "name": "coverage",
      "result": "success",
      "result_code": 1,
      "signatures": [
        "coverage-3.11"
      ]
    },
    {
      "args": {},
      "name": "coverage",
      "result": "success",
      "result_code": 1,
      "signatures": [
        "coverage-3.12"
      ]
    },
    {
      "args": {},
      "name": "coverage",
      "result": "skipped",
      "result_code": 2,
      "signatures": [
        "coverage-3.13"
      ]
    }
  ]
}